pypnm/__init__.py
pypnm/cli.py
pypnm/py.typed
pypnm/version.py
pypnm/api/main.py
pypnm/api/routes/advance/analysis/report/multi_analysis_rpt.py
pypnm/api/routes/advance/analysis/signal_analysis/group_delay_calculator.py
pypnm/api/routes/advance/analysis/signal_analysis/multi_chan_est_singnal_analysis.py
pypnm/api/routes/advance/analysis/signal_analysis/multi_ofdm_chan_signal_analysis.py
pypnm/api/routes/advance/analysis/signal_analysis/multi_ofdma_pre_eq_signal_analysis.py
pypnm/api/routes/advance/analysis/signal_analysis/multi_rxmer_signal_analysis.py
pypnm/api/routes/advance/analysis/signal_analysis/detection/anolamaly/heatmap_anomaly_detection.py
pypnm/api/routes/advance/analysis/signal_analysis/detection/echo/echo_detector.py
pypnm/api/routes/advance/analysis/signal_analysis/detection/echo/ifft.py
pypnm/api/routes/advance/analysis/signal_analysis/detection/echo/phase_slope.py
pypnm/api/routes/advance/analysis/signal_analysis/detection/echo/type.py
pypnm/api/routes/advance/analysis/signal_analysis/detection/lte/phase_slope_lte_detection.py
pypnm/api/routes/advance/common/capture_data_aggregator.py
pypnm/api/routes/advance/common/capture_service.py
pypnm/api/routes/advance/common/operation_manager.py
pypnm/api/routes/advance/common/operation_state.py
pypnm/api/routes/advance/common/transactionsCollection.py
pypnm/api/routes/advance/common/abstract/service.py
pypnm/api/routes/advance/common/schema/common_capture_schema.py
pypnm/api/routes/advance/common/types/types.py
pypnm/api/routes/advance/multi_ds_chan_est/router.py
pypnm/api/routes/advance/multi_ds_chan_est/schemas.py
pypnm/api/routes/advance/multi_ds_chan_est/service.py
pypnm/api/routes/advance/multi_rxmer/router.py
pypnm/api/routes/advance/multi_rxmer/schemas.py
pypnm/api/routes/advance/multi_rxmer/service.py
pypnm/api/routes/advance/multi_us_ofdma_pre_eq/router.py
pypnm/api/routes/advance/multi_us_ofdma_pre_eq/schemas.py
pypnm/api/routes/advance/multi_us_ofdma_pre_eq/service.py
pypnm_docsis-1.1.13.0.dist-info/licenses/LICENSE
pypnm_docsis-1.1.13.0.dist-info/licenses/NOTICE
pypnm_docsis-1.1.13.0.dist-info/METADATA
pypnm_docsis-1.1.13.0.dist-info/WHEEL
pypnm_docsis-1.1.13.0.dist-info/entry_points.txt
pypnm_docsis-1.1.13.0.dist-info/top_level.txt
pypnm_docsis-1.1.13.0.dist-info/RECORD
