Metadata-Version: 2.4
Name: pypnm-docsis
Version: 1.1.13.0
Summary: DOCSIS 3.x/4.0 Proactive Network Maintenance Toolkit
Author-email: Maurice Garcia <pypnm.docsis@gmail.com>
License-Expression: Apache-2.0
Project-URL: Homepage, https://www.pypnm.io
Project-URL: Repository, https://github.com/PyPNMApps/PyPNM
Project-URL: Bug-Tracker, https://github.com/PyPNMApps/PyPNM/issues
Project-URL: Documentation, https://www.pypnm.io
Classifier: Programming Language :: Python :: 3
Classifier: Programming Language :: Python :: 3 :: Only
Classifier: Programming Language :: Python :: 3.10
Classifier: Programming Language :: Python :: 3.11
Classifier: Programming Language :: Python :: 3.12
Classifier: Programming Language :: Python :: 3.13
Classifier: Operating System :: OS Independent
Classifier: Framework :: FastAPI
Classifier: Topic :: System :: Networking
Classifier: Typing :: Typed
Requires-Python: >=3.10
License-File: LICENSE
License-File: NOTICE
Requires-Dist: fastapi==0.115.12
Requires-Dist: uvicorn[standard]==0.34.2
Requires-Dist: python-multipart>=0.0.20
Requires-Dist: numpy==2.2.6
Requires-Dist: scipy==1.15.1
Requires-Dist: pydantic<2.13,>=2.12.4
Requires-Dist: pysmi==1.6.1
Requires-Dist: pysnmp==7.1.17
Requires-Dist: python-dotenv>=1.0.0
Requires-Dist: requests==2.32.3
Requires-Dist: pandas==2.2.3
Requires-Dist: paramiko==3.5.1
Requires-Dist: tftpy==0.8.5
Requires-Dist: matplotlib==3.10.8
Requires-Dist: typing-extensions>=4.10.0
Provides-Extra: dev
Requires-Dist: pytest>=8.0.0; extra == "dev"
Requires-Dist: pytest-cov>=5.0.0; extra == "dev"
Requires-Dist: pytest-asyncio>=0.23.5; extra == "dev"
Requires-Dist: black>=24.0.0; extra == "dev"
Requires-Dist: pydantic-settings>=2.6.0; extra == "dev"
Requires-Dist: ruff>=0.14.7; extra == "dev"
Requires-Dist: pycycle>=0.0.8; extra == "dev"
Requires-Dist: pyright>=1.1.407; extra == "dev"
Requires-Dist: pyyaml>=6.0.2; extra == "dev"
Provides-Extra: docs
Requires-Dist: mkdocs>=1.6; extra == "docs"
Requires-Dist: mkdocs-material>=9.5; extra == "docs"
Requires-Dist: pymdown-extensions>=10.8; extra == "docs"
Provides-Extra: reports
Dynamic: license-file
